visens/__init__.py
visens/image.py
visens/imviewer.py
visens/instrument_view.py
visens/load.py
visens/preview.py
visens/slicer.py
visens/tof.py
visens/volume.py
visens/xy_vs_tof.py
visens-0.1.7.dist-info/LICENSE
visens-0.1.7.dist-info/METADATA
visens-0.1.7.dist-info/WHEEL
visens-0.1.7.dist-info/top_level.txt
visens-0.1.7.dist-info/RECORD
